<?xml version="1.0" encoding="utf-8"?>
<!--NSI Web Service v6.16.0-->
<message:Structure xmlns:message="http://www.sdmx.org/resources/sdmxml/schemas/v2_1/message" xmlns:structure="http://www.sdmx.org/resources/sdmxml/schemas/v2_1/structure" xmlns:common="http://www.sdmx.org/resources/sdmxml/schemas/v2_1/common">
  <message:Header>
    <message:ID>IDREF773</message:ID>
    <message:Test>false</message:Test>
    <message:Prepared>2022-01-17T16:26:58.8293045+01:00</message:Prepared>
    <message:Sender id="Unknown" />
    <message:Receiver id="Unknown" />
  </message:Header>
  <message:Structures>
    <structure:Constraints>
      <structure:ContentConstraint id="CC" urn="urn:sdmx:org.sdmx.infomodel.registry.ContentConstraint=SDMX:CC(1.0)" agencyID="SDMX" version="1.0" type="Actual">
        <common:Annotations>
          <common:Annotation id="obs_count">
            <common:AnnotationTitle>287508</common:AnnotationTitle>
            <common:AnnotationType>sdmx_metrics</common:AnnotationType>
          </common:Annotation>
        </common:Annotations>
        <common:Name xml:lang="en">Autogenerated content constraint</common:Name>
        <structure:ConstraintAttachment>
          <structure:Dataflow>
            <Ref id="97_79" version="1.2" agencyID="IT1" package="datastructure" class="Dataflow" />
          </structure:Dataflow>
        </structure:ConstraintAttachment>
        <structure:CubeRegion include="true">
          <common:KeyValue id="FREQ">
            <common:Value>A</common:Value>
          </common:KeyValue>
          <common:KeyValue id="ATT_ECO">
            <common:Value>0010</common:Value>
            <common:Value>01</common:Value>
            <common:Value>02</common:Value>
            <common:Value>05</common:Value>
            <common:Value>10</common:Value>
            <common:Value>11</common:Value>
            <common:Value>12</common:Value>
            <common:Value>13</common:Value>
            <common:Value>14</common:Value>
            <common:Value>15</common:Value>
            <common:Value>16</common:Value>
            <common:Value>17</common:Value>
            <common:Value>18</common:Value>
            <common:Value>19</common:Value>
            <common:Value>20</common:Value>
            <common:Value>21</common:Value>
            <common:Value>22</common:Value>
            <common:Value>23</common:Value>
            <common:Value>24</common:Value>
            <common:Value>25</common:Value>
            <common:Value>26</common:Value>
            <common:Value>27</common:Value>
            <common:Value>28</common:Value>
            <common:Value>29</common:Value>
            <common:Value>30</common:Value>
            <common:Value>31</common:Value>
            <common:Value>31_32</common:Value>
            <common:Value>32</common:Value>
            <common:Value>33</common:Value>
            <common:Value>34</common:Value>
            <common:Value>35</common:Value>
            <common:Value>36</common:Value>
            <common:Value>37</common:Value>
            <common:Value>40</common:Value>
            <common:Value>41</common:Value>
            <common:Value>45</common:Value>
            <common:Value>50</common:Value>
            <common:Value>51</common:Value>
            <common:Value>52</common:Value>
            <common:Value>55</common:Value>
            <common:Value>60</common:Value>
            <common:Value>60_63</common:Value>
            <common:Value>61</common:Value>
            <common:Value>61_63</common:Value>
            <common:Value>62</common:Value>
            <common:Value>63</common:Value>
            <common:Value>64</common:Value>
            <common:Value>65</common:Value>
            <common:Value>66</common:Value>
            <common:Value>67</common:Value>
            <common:Value>70</common:Value>
            <common:Value>71</common:Value>
            <common:Value>72</common:Value>
            <common:Value>73</common:Value>
            <common:Value>74</common:Value>
            <common:Value>75</common:Value>
            <common:Value>80</common:Value>
            <common:Value>85</common:Value>
            <common:Value>90</common:Value>
            <common:Value>91</common:Value>
            <common:Value>92</common:Value>
            <common:Value>93</common:Value>
            <common:Value>95</common:Value>
            <common:Value>A</common:Value>
            <common:Value>B</common:Value>
            <common:Value>C</common:Value>
            <common:Value>CA</common:Value>
            <common:Value>CB</common:Value>
            <common:Value>D</common:Value>
            <common:Value>DA</common:Value>
            <common:Value>DB</common:Value>
            <common:Value>DC</common:Value>
            <common:Value>DD</common:Value>
            <common:Value>DE</common:Value>
            <common:Value>DF</common:Value>
            <common:Value>DG</common:Value>
            <common:Value>DH</common:Value>
            <common:Value>DI</common:Value>
            <common:Value>DJ</common:Value>
            <common:Value>DK</common:Value>
            <common:Value>DL</common:Value>
            <common:Value>DM</common:Value>
            <common:Value>DN</common:Value>
            <common:Value>E</common:Value>
            <common:Value>F</common:Value>
            <common:Value>G</common:Value>
            <common:Value>H</common:Value>
            <common:Value>I</common:Value>
            <common:Value>J</common:Value>
            <common:Value>K</common:Value>
            <common:Value>L</common:Value>
            <common:Value>M</common:Value>
            <common:Value>N</common:Value>
            <common:Value>O</common:Value>
            <common:Value>P</common:Value>
            <common:Value>Z</common:Value>
          </common:KeyValue>
          <common:KeyValue id="CAUSA">
            <common:Value>HEA</common:Value>
            <common:Value>OTH</common:Value>
            <common:Value>TOT</common:Value>
            <common:Value>TRA</common:Value>
            <common:Value>Z</common:Value>
          </common:KeyValue>
          <common:KeyValue id="INQUINANTI">
            <common:Value>Zn</common:Value>
            <common:Value>N2O</common:Value>
            <common:Value>Cu</common:Value>
            <common:Value>Cd</common:Value>
            <common:Value>NH3</common:Value>
            <common:Value>Cr</common:Value>
            <common:Value>CH4</common:Value>
            <common:Value>Pb</common:Value>
            <common:Value>PM10</common:Value>
            <common:Value>NOX</common:Value>
            <common:Value>As</common:Value>
            <common:Value>CO</common:Value>
            <common:Value>Se</common:Value>
            <common:Value>Hg</common:Value>
            <common:Value>SOX</common:Value>
            <common:Value>Ni</common:Value>
            <common:Value>CO2</common:Value>
            <common:Value>PM2_5</common:Value>
            <common:Value>COVNM</common:Value>
          </common:KeyValue>
          <common:KeyValue id="ITTER107">
            <common:Value>IT</common:Value>
          </common:KeyValue>
          <common:KeyValue id="RACNAMUNF">
            <common:Value>R1</common:Value>
            <common:Value>R2</common:Value>
            <common:Value>R3</common:Value>
            <common:Value>R4</common:Value>
            <common:Value>Z</common:Value>
          </common:KeyValue>
          <common:KeyValue id="TIP_AGGR">
            <common:Value>AE_T</common:Value>
            <common:Value>AEHM_K</common:Value>
            <common:Value>EI_TXFTE</common:Value>
            <common:Value>EI_TXO</common:Value>
            <common:Value>EI_TXVA</common:Value>
            <common:Value>EIHM_KXFTE</common:Value>
            <common:Value>EIHM_KXO</common:Value>
            <common:Value>EIHM_KXVA</common:Value>
          </common:KeyValue>
          <common:KeyValue id="EDI">
            <common:Value>2010M12</common:Value>
            <common:Value>2011M12</common:Value>
          </common:KeyValue>
          <common:KeyValue id="VAL">
            <common:Value>L</common:Value>
            <common:Value>Z</common:Value>
          </common:KeyValue>
        </structure:CubeRegion>
        <structure:ReferencePeriod startTime="1990-01-01T00:00:00Z" endTime="2009-01-01T00:00:00Z" />
      </structure:ContentConstraint>
    </structure:Constraints>
  </message:Structures>
</message:Structure>